package_fileDO/FileDO.py
package_fileDO/__init__.py
package_fileDO-0.1.2.dist-info/LICENSE.txt
package_fileDO-0.1.2.dist-info/METADATA
package_fileDO-0.1.2.dist-info/WHEEL
package_fileDO-0.1.2.dist-info/top_level.txt
package_fileDO-0.1.2.dist-info/RECORD
