Metadata-Version: 2.1
Name: package_fileDO
Version: 0.1.2
Summary: A python SDK for ioc-ic
Home-page: https://github.com/whalecui1014
Author: Cui Jingyu
Author-email: 1808662399@qq.com
License: MIT
Classifier: Development Status :: 3 - Alpha
Classifier: Intended Audience :: Developers
Classifier: License :: OSI Approved :: MIT License
Classifier: Programming Language :: Python :: 3
Classifier: Programming Language :: Python :: 3.7
Classifier: Programming Language :: Python :: 3.8
Classifier: Programming Language :: Python :: 3.9
License-File: LICENSE.txt
Requires-Dist: requests
